aide_render/__init__.py
aide_render/import_dicts.py
aide_render/render.py
aide_render/yaml.py
aide_render-0.0.1.dist-info/DESCRIPTION.rst
aide_render-0.0.1.dist-info/METADATA
aide_render-0.0.1.dist-info/RECORD
aide_render-0.0.1.dist-info/WHEEL
aide_render-0.0.1.dist-info/metadata.json
aide_render-0.0.1.dist-info/top_level.txt
