Metadata-Version: 2.0
Name: aide-render
Version: 0.0.1
Summary: aide_render
Home-page: https://github.com/AguaClara/aide_render
Author: AguaClara
Author-email: aguaclara@cornell.edu
License: Apache License (2.0)
Download-URL: https://github.com/AguaClara/aide_render/archive/0.0.0.tar.gz
Platform: UNKNOWN
Requires-Dist: pyyaml
Requires-Dist: jinja2
Requires-Dist: aide-design
Requires-Dist: numpy
